topological_recursion
