Metadata-Version: 2.1
Name: topological-recursion
Version: 0.0a2
Summary: Topological recursion
Home-page: https://gitlab.com/toprec/toprec
Author: Vincent Delecroix, Bertrand Eynard, Dimitrios Mitsios
Author-email: bertrand.eynard@ipht.fr
License: GPLv2+
Keywords: topological-recursion surfaces geometry
Platform: UNKNOWN
Classifier: Development Status :: 2 - Pre-Alpha
Classifier: Intended Audience :: Science/Research
Classifier: Topic :: Scientific/Engineering :: Mathematics
Classifier: License :: OSI Approved :: GNU General Public License v2 or later (GPLv2+)
Classifier: Programming Language :: Python :: 3
